{
  "data": [
    {
      "messageId": 1,
      "aircraftRegistration": "AIRCERAFT-1",
      "flight": "JKJK",
      "desk": "KL;;",
      "deskCategory": "KMCV",
      "escalated": "V",
      "acknowledge": "VKOO",
      "acknowledgedBy": "V",
      "received": "V",
      "priority": "V",
      "isPublished": 0,
      "id": 1
    },
    {
      "messageId": 2,
      "aircraftRegistration": "njk",
      "flight": "",
      "desk": "",
      "deskCategory": "",
      "escalated": "",
      "acknowledge": "",
      "acknowledgedBy": "",
      "received": "",
      "priority": "",
      "isPublished": 0,
      "id": 2
    },
    {
      "widgetId": 3,
      "widgetName": "",
      "widgetTag": "",
      "widgetStatus": "",
      "widgetSize": "",
      "description": "",
      "id": 3
    }
  ]
}